pyhockeystats/__init__.py
pyhockeystats/__main__.py
pyhockeystats/hockeydatabase.py
pyhockeystats/hockeydwnload.py
pyhockeystats/hockeyfunctions.py
pyhockeystats/hockeyoopfuncs.py
pyhockeystats/hockeyshortcuts.py
pyhockeystats/versioninfo.py
pyhockeystats/sgmldtd/__init__.py
pyhockeystats/xmldtd/__init__.py
pyhockeystats-0.10.10.data/scripts/mkhockeytool3.py
pyhockeystats-0.10.10.dist-info/licenses/LICENSE
pyhockeystats-0.10.10.dist-info/licenses/LICENSE.md
pyhockeystats-0.10.10.dist-info/METADATA
pyhockeystats-0.10.10.dist-info/WHEEL
pyhockeystats-0.10.10.dist-info/top_level.txt
pyhockeystats-0.10.10.dist-info/zip-safe
pyhockeystats-0.10.10.dist-info/RECORD
