Metadata-Version: 2.4
Name: PyHockeyStats
Version: 0.10.10
Summary: Just a test script dealing with hockey games and stats.
Home-page: https://github.com/GameMaker2k/Neo-Hockey-Test
Download-URL: https://github.com/GameMaker2k/Neo-Hockey-Test/archive/master.tar.gz
Author: Kazuki Przyborowski
Author-email: Kazuki Przyborowski <kazuki.przyborowski@gmail.com>
Maintainer: Kazuki Przyborowski
Maintainer-email: kazuki.przyborowski@gmail.com
License: BSD-3-Clause
Platform: OS Independent
License-File: LICENSE
License-File: LICENSE.md
Dynamic: author
Dynamic: download-url
Dynamic: home-page
Dynamic: license-file
Dynamic: maintainer
Dynamic: maintainer-email
Dynamic: platform
